Metadata-Version: 2.1
Name: pyDGSA
Version: 1.0.3
Summary: Python implementation of distance-based generalized sensitivity analysis (DGSA)
Home-page: https://github.com/zperzan/pyDGSA
Author: Zach Perzan
Author-email: zperzan@stanford.edu
License: GPL
Classifier: Programming Language :: Python :: 3
Classifier: License :: OSI Approved :: GNU General Public License (GPL)
Requires-Python: >=3.7
License-File: LICENSE
